<DATA>
	<ROW>
		<EMP_NO>7369</EMP_NO>
		<APELLIDO>SÁNCHEZ</APELLIDO>
		<OFICIO>EMPLEADO</OFICIO>
		<DIR>7902</DIR>
		<FECHA_ALT>1990-12-17</FECHA_ALT>
		<SALARIO>1040.00</SALARIO>
		<COMISION>NULL</COMISION>
		<DEPT_NO>20</DEPT_NO>
	</ROW>

	<ROW>
		<EMP_NO>7499</EMP_NO>
		<APELLIDO>ARROYO</APELLIDO>
		<OFICIO>VENDEDOR</OFICIO>
		<DIR>7698</DIR>
		<FECHA_ALT>1990-02-20</FECHA_ALT>
		<SALARIO>1500.00</SALARIO>
		<COMISION>390.00</COMISION>
		<DEPT_NO>30</DEPT_NO>
	</ROW>

	<ROW>
		<EMP_NO>7521</EMP_NO>
		<APELLIDO>SALA</APELLIDO>
		<OFICIO>VENDEDOR</OFICIO>
		<DIR>7698</DIR>
		<FECHA_ALT>1991-02-22</FECHA_ALT>
		<SALARIO>1625.00</SALARIO>
		<COMISION>650.00</COMISION>
		<DEPT_NO>30</DEPT_NO>
	</ROW>

	<ROW>
		<EMP_NO>7566</EMP_NO>
		<APELLIDO>JIMÉNEZ</APELLIDO>
		<OFICIO>DIRECTOR</OFICIO>
		<DIR>7839</DIR>
		<FECHA_ALT>1991-04-02</FECHA_ALT>
		<SALARIO>2900.00</SALARIO>
		<COMISION>NULL</COMISION>
		<DEPT_NO>20</DEPT_NO>
	</ROW>

	<ROW>
		<EMP_NO>7654</EMP_NO>
		<APELLIDO>MARTÍN</APELLIDO>
		<OFICIO>VENDEDOR</OFICIO>
		<DIR>7698</DIR>
		<FECHA_ALT>1991-09-29</FECHA_ALT>
		<SALARIO>1600.00</SALARIO>
		<COMISION>1020.00</COMISION>
		<DEPT_NO>30</DEPT_NO>
	</ROW>

	<ROW>
		<EMP_NO>7698</EMP_NO>
		<APELLIDO>NEGRO</APELLIDO>
		<OFICIO>DIRECTOR</OFICIO>
		<DIR>7839</DIR>
		<FECHA_ALT>1991-05-01</FECHA_ALT>
		<SALARIO>3005.00</SALARIO>
		<COMISION>NULL</COMISION>
		<DEPT_NO>30</DEPT_NO>
	</ROW>

	<ROW>
		<EMP_NO>7782</EMP_NO>
		<APELLIDO>CEREZO</APELLIDO>
		<OFICIO>DIRECTOR</OFICIO>
		<DIR>7839</DIR>
		<FECHA_ALT>1991-06-09</FECHA_ALT>
		<SALARIO>2885.00</SALARIO>
		<COMISION>NULL</COMISION>
		<DEPT_NO>10</DEPT_NO>
	</ROW>

	<ROW>
		<EMP_NO>7788</EMP_NO>
		<APELLIDO>GIL</APELLIDO>
		<OFICIO>ANALISTA</OFICIO>
		<DIR>7566</DIR>
		<FECHA_ALT>1991-11-09</FECHA_ALT>
		<SALARIO>3000.00</SALARIO>
		<COMISION>NULL</COMISION>
		<DEPT_NO>20</DEPT_NO>
	</ROW>

	<ROW>
		<EMP_NO>7839</EMP_NO>
		<APELLIDO>REY</APELLIDO>
		<OFICIO>PRESIDENTE</OFICIO>
		<DIR>NULL</DIR>
		<FECHA_ALT>1991-11-17</FECHA_ALT>
		<SALARIO>4100.00</SALARIO>
		<COMISION>NULL</COMISION>
		<DEPT_NO>10</DEPT_NO>
	</ROW>

	<ROW>
		<EMP_NO>7844</EMP_NO>
		<APELLIDO>TOVAR</APELLIDO>
		<OFICIO>VENDEDOR</OFICIO>
		<DIR>7698</DIR>
		<FECHA_ALT>1991-09-08</FECHA_ALT>
		<SALARIO>1350.00</SALARIO>
		<COMISION>0.00</COMISION>
		<DEPT_NO>30</DEPT_NO>
	</ROW>

	<ROW>
		<EMP_NO>7876</EMP_NO>
		<APELLIDO>ALONSO</APELLIDO>
		<OFICIO>EMPLEADO</OFICIO>
		<DIR>7788</DIR>
		<FECHA_ALT>1991-09-23</FECHA_ALT>
		<SALARIO>1430.00</SALARIO>
		<COMISION>NULL</COMISION>
		<DEPT_NO>20</DEPT_NO>
	</ROW>

	<ROW>
		<EMP_NO>7900</EMP_NO>
		<APELLIDO>JIMENO</APELLIDO>
		<OFICIO>EMPLEADO</OFICIO>
		<DIR>7698</DIR>
		<FECHA_ALT>1991-12-03</FECHA_ALT>
		<SALARIO>1335.00</SALARIO>
		<COMISION>NULL</COMISION>
		<DEPT_NO>30</DEPT_NO>
	</ROW>

	<ROW>
		<EMP_NO>7902</EMP_NO>
		<APELLIDO>FERNÁNDEZ</APELLIDO>
		<OFICIO>ANALISTA</OFICIO>
		<DIR>7566</DIR>
		<FECHA_ALT>1991-12-03</FECHA_ALT>
		<SALARIO>3000.00</SALARIO>
		<COMISION>NULL</COMISION>
		<DEPT_NO>20</DEPT_NO>
	</ROW>

	<ROW>
		<EMP_NO>7934</EMP_NO>
		<APELLIDO>MUÑOZ</APELLIDO>
		<OFICIO>EMPLEADO</OFICIO>
		<DIR>7782</DIR>
		<FECHA_ALT>1992-01-23</FECHA_ALT>
		<SALARIO>1690.00</SALARIO>
		<COMISION>NULL</COMISION>
		<DEPT_NO>10</DEPT_NO>
	</ROW>

	<ROW>
		<EMP_NO>7935</EMP_NO>
		<APELLIDO>GATES</APELLIDO>
		<OFICIO>EMPLEADO</OFICIO>
		<DIR>7782</DIR>
		<FECHA_ALT>1992-01-23</FECHA_ALT>
		<SALARIO>1690.00</SALARIO>
		<COMISION>NULL</COMISION>
		<DEPT_NO>50</DEPT_NO>
	</ROW>
</DATA>
